k3m/__init__.py
k3m/clusters.py
k3m/commands.py
k3m/console.py
k3m/migrate_json_to_db.py
k3m/models.py
k3m/multipass.py
k3m/utils.py
k3m-0.2.0.dist-info/LICENSE
k3m-0.2.0.dist-info/METADATA
k3m-0.2.0.dist-info/WHEEL
k3m-0.2.0.dist-info/entry_points.txt
k3m-0.2.0.dist-info/RECORD
