Metadata-Version: 2.3
Name: k3m
Version: 0.2.0
Summary: Lightweight k3s cluster manager
License: GPL-3.0-or-later
Keywords: k3s,kubernetes,cluster,multipass,devops
Author: Bruno Bernard
Author-email: brunobernard@duck.com
Requires-Python: >=3.11,<4.0
Classifier: Development Status :: 4 - Beta
Classifier: Environment :: Console
Classifier: Intended Audience :: Developers
Classifier: Intended Audience :: System Administrators
Classifier: License :: OSI Approved :: GNU General Public License v3 or later (GPLv3+)
Classifier: Programming Language :: Python :: 3
Classifier: Programming Language :: Python :: 3.11
Classifier: Programming Language :: Python :: 3.12
Classifier: Programming Language :: Python :: 3.13
Classifier: Topic :: Software Development :: Build Tools
Classifier: Topic :: System :: Systems Administration
Requires-Dist: click (>=8.1.7,<9.0.0)
Requires-Dist: halo (>=0.0.31,<0.0.32)
Requires-Dist: peewee (>=3.17.9,<4.0.0)
Requires-Dist: pydantic (>=2.6.3,<3.0.0)
Requires-Dist: rich (>=13.7.0,<14.0.0)
Project-URL: Repository, https://github.com/eznix86/k3m
